[
  {"name": "글렌 굴드", "keyword": ["바흐", "골드베르크", "캐나다", "피아노"]},
  {"name": "호로비츠", "keyword": ["피아노", "비르투오소", "라흐마니노프", "러시아"]},
  {"name": "루빈스타인", "keyword": ["쇼팽", "녹턴", "폴란드", "낭만"]},
  {"name": "아르투르 루빈스타인", "keyword": ["쇼팽", "폴로네이즈", "마주르카", "피아노"]},
  {"name": "마르타 아르헤리치", "keyword": ["피아노", "아르헨티나", "협주곡", "정열"]},
  {"name": "조성진", "keyword": ["쇼팽", "피아노", "콩쿠르", "한국"]},
  {"name": "랑랑", "keyword": ["피아노", "협주곡", "중국", "베토벤"]},
  {"name": "임윤찬", "keyword": ["피아노", "한국", "클리번", "젊은"]},
  {"name": "다니엘 바렌보임", "keyword": ["지휘", "피아노", "베를린", "바그너"]},
  {"name": "정명훈", "keyword": ["지휘", "오케스트라", "서울시향", "프랑스"]},
  {"name": "카라얀", "keyword": ["지휘", "베를린필", "오케스트라", "오스트리아"]},
  {"name": "번스타인", "keyword": ["지휘", "뉴욕필", "웨스트사이드", "미국"]},
  {"name": "토스카니니", "keyword": ["지휘", "NBC", "이탈리아", "베르디"]},
  {"name": "파바로티", "keyword": ["테너", "오페라", "이탈리아", "아리아"]},
  {"name": "마리아 칼라스", "keyword": ["소프라노", "오페라", "벨칸토", "그리스"]},
  {"name": "이차크 펄만", "keyword": ["바이올린", "이스라엘", "협주곡", "브람스"]},
  {"name": "요요마", "keyword": ["첼로", "바흐", "실크로드", "중국"]},
  {"name": "하이페츠", "keyword": ["바이올린", "비르투오소", "러시아", "협주곡"]},
  {"name": "로스트로포비치", "keyword": ["첼로", "러시아", "쇼스타코비치", "프로코피예프"]},
  {"name": "정경화", "keyword": ["바이올린", "한국", "차이콥스키", "콩쿠르"]},
  {"name": "장영주", "keyword": ["바이올린", "한국", "프랑크", "소나타"]},
  {"name": "김대진", "keyword": ["피아노", "한국", "차이콥스키", "콩쿠르"]},
  {"name": "백건우", "keyword": ["피아노", "한국", "쇼팽", "브람스"]},
  {"name": "한동일", "keyword": ["바이올린", "한국", "콩쿠르", "실내악"]},
  {"name": "조수미", "keyword": ["소프라노", "한국", "콜로라투라", "오페라"]},
  {"name": "홍혜경", "keyword": ["소프라노", "한국", "리트", "독일가곡"]},
  {"name": "신영옥", "keyword": ["소프라노", "한국", "오페라", "이탈리아"]},
  {"name": "김우경", "keyword": ["바리톤", "한국", "리트", "성악"]},
  {"name": "프랑 리스트", "keyword": ["피아노", "비르투오소", "헝가리", "초절기교"]},
  {"name": "클라라 슈만", "keyword": ["피아노", "작곡", "독일", "로베르트"]},
  {"name": "야샤 하이페츠", "keyword": ["바이올린", "러시아", "기교", "협주곡"]},
  {"name": "파블로 카잘스", "keyword": ["첼로", "바흐", "스페인", "무반주"]},
  {"name": "디누 리파티", "keyword": ["피아노", "루마니아", "쇼팽", "단명"]},
  {"name": "클라우디오 아라우", "keyword": ["피아노", "칠레", "베토벤", "브람스"]},
  {"name": "알프레드 브렌델", "keyword": ["피아노", "오스트리아", "모차르트", "슈베르트"]},
  {"name": "다비드 오이스트라흐", "keyword": ["바이올린", "소련", "브람스", "협주곡"]},
  {"name": "옐레나 오브라즈초바", "keyword": ["메조소프라노", "러시아", "오페라", "볼쇼이"]},
  {"name": "플라시도 도밍고", "keyword": ["테너", "스페인", "오페라", "3대테너"]},
  {"name": "호세 카레라스", "keyword": ["테너", "스페인", "오페라", "3대테너"]},
  {"name": "브린 털펠", "keyword": ["바리톤", "웨일즈", "리트", "성악"]}
]
